misclogic/__init__.py
misclogic-0.0.1.dist-info/DESCRIPTION.rst
misclogic-0.0.1.dist-info/METADATA
misclogic-0.0.1.dist-info/RECORD
misclogic-0.0.1.dist-info/WHEEL
misclogic-0.0.1.dist-info/metadata.json
misclogic-0.0.1.dist-info/top_level.txt
